logscanner-0.9.3.dist-info/METADATA
logscanner-0.9.3.dist-info/WHEEL
logscanner-0.9.3.dist-info/entry_points.txt
logscanner-0.9.3.dist-info/licenses/LICENSE
logscanner/__init__.py
logscanner/logging.py
logscanner/py.typed
logscanner/template/logscanner.html
logscanner-0.9.3.dist-info/RECORD
